shapeio/__init__.py
shapeio/decoder.py
shapeio/encoder.py
shapeio/shape.py
shapeio/shapeio.py
shapeio-0.5.0b3.dist-info/licenses/LICENSE
tests/__init__.py
tests/conftest.py
tests/test_animation.py
tests/test_animation_nodes.py
tests/test_block_parsers.py
tests/test_block_serializers.py
tests/test_colour.py
tests/test_controller.py
tests/test_cullable_prims.py
tests/test_distance_level_selection.py
tests/test_distance_levels_header.py
tests/test_geometry_info.py
tests/test_geometry_node.py
tests/test_image.py
tests/test_indexed_trilist.py
tests/test_key_position.py
tests/test_light_material.py
tests/test_light_model_cfg.py
tests/test_matrix.py
tests/test_named_filter_mode.py
tests/test_named_shader.py
tests/test_point.py
tests/test_prim_state.py
tests/test_primitives_list.py
tests/test_shape.py
tests/test_shape_header.py
tests/test_shapeio.py
tests/test_sub_object_header.py
tests/test_texture.py
tests/test_uv_op.py
tests/test_uv_point.py
tests/test_vector.py
tests/test_vertex.py
tests/test_vertex_set.py
tests/test_volume_sphere.py
tests/test_vtx_state.py
shapeio-0.5.0b3.dist-info/METADATA
shapeio-0.5.0b3.dist-info/WHEEL
shapeio-0.5.0b3.dist-info/top_level.txt
shapeio-0.5.0b3.dist-info/RECORD
