Metadata-Version: 2.4
Name: shapeio
Version: 0.5.0b3
Summary: A Python module to read MSTS/ORTS shape files into Python data structures and write them back to text.
Author: Peter Grønbæk Andersen
Author-email: Peter Grønbæk Andersen <peter@grnbk.io>
License: GNU GPL v3
Project-URL: Homepage, https://github.com/pgroenbaek/shapeio
Project-URL: Issues, https://github.com/pgroenbaek/shapeio/issues
Project-URL: Source, https://github.com/pgroenbaek/shapeio
Classifier: Programming Language :: Python :: 3
Classifier: License :: OSI Approved :: GNU General Public License v3 or later (GPLv3+)
Classifier: Operating System :: OS Independent
Requires-Python: >=3.7
Requires-Dist: numpy
Dynamic: author
Dynamic: requires-python
